ovh_cli/__init__.py
ovh_cli/account.py
ovh_cli/ovh_cli.py
ovh_cli/zone_manager.py
ovh_cli_yma-1.0.0.dist-info/LICENSE
ovh_cli_yma-1.0.0.dist-info/LICENSE.txt
ovh_cli_yma-1.0.0.dist-info/METADATA
ovh_cli_yma-1.0.0.dist-info/WHEEL
ovh_cli_yma-1.0.0.dist-info/entry_points.txt
ovh_cli_yma-1.0.0.dist-info/top_level.txt
ovh_cli_yma-1.0.0.dist-info/RECORD
