Metadata-Version: 2.1
Name: ovh-cli-yma
Version: 1.0.0
Summary: An ovh command line tool
Author-email: Yusef Maali <contact@yusefmaali.net>
License: MIT
Project-URL: homepage, https://github.com/yusefmaali/ovh-cli
Project-URL: repository, https://github.com/yusefmaali/ovh-cli
Project-URL: changelog, https://github.com/yusefmaali/ovh-cli/blob/master/CHANGELOG.rst
Project-URL: download, https://github.com/yusefmaali/ovh-cli/tarball/1.0.0
Keywords: ovh,api,cli,tool,wrapper
Classifier: Intended Audience :: Developers
Classifier: License :: OSI Approved :: MIT License
Classifier: Development Status :: 5 - Production/Stable
Classifier: Operating System :: OS Independent
Classifier: Programming Language :: Python
Classifier: Programming Language :: Python :: 3
Classifier: Programming Language :: Python :: 3.7
Classifier: Programming Language :: Python :: 3.8
Classifier: Programming Language :: Python :: 3.9
Classifier: Programming Language :: Python :: 3.10
Classifier: Programming Language :: Python :: 3.11
Classifier: Natural Language :: English
Requires-Python: >=3.7
License-File: LICENSE
License-File: LICENSE.txt
Requires-Dist: ovh ~=1.1.0
